council/__init__.py
council/py.typed
council/agent_tests/__init__.py
council/agent_tests/agent_tests.py
council/agents/__init__.py
council/agents/agent.py
council/agents/agent_chain.py
council/agents/agent_result.py
council/chains/__init__.py
council/chains/chain.py
council/chains/chain_base.py
council/contexts/__init__.py
council/contexts/_agent_context.py
council/contexts/_agent_context_store.py
council/contexts/_agent_iteration_context_store.py
council/contexts/_budget.py
council/contexts/_cancellation_token.py
council/contexts/_chain_context.py
council/contexts/_chat_history.py
council/contexts/_chat_message.py
council/contexts/_composite_message_collection.py
council/contexts/_context_base.py
council/contexts/_context_logger.py
council/contexts/_execution_context.py
council/contexts/_execution_log.py
council/contexts/_execution_log_entry.py
council/contexts/_llm_context.py
council/contexts/_message_collection.py
council/contexts/_message_list.py
council/contexts/_monitor.py
council/contexts/_monitorable.py
council/contexts/_monitored.py
council/contexts/_monitored_budget.py
council/contexts/_monitored_message_list.py
council/contexts/_scorer_context.py
council/contexts/_skill_context.py
council/controllers/__init__.py
council/controllers/basic_controller.py
council/controllers/controller_base.py
council/controllers/execution_unit.py
council/controllers/llm_controller.py
council/evaluators/__init__.py
council/evaluators/basic_evaluator.py
council/evaluators/evaluator_base.py
council/evaluators/llm_evaluator.py
council/filters/__init__.py
council/filters/basic_filter.py
council/filters/filter_base.py
council/filters/llm_filter.py
council/llm/__init__.py
council/llm/base/__init__.py
council/llm/base/llm_answer.py
council/llm/base/llm_base.py
council/llm/base/llm_config_object.py
council/llm/base/llm_cost.py
council/llm/base/llm_exception.py
council/llm/base/llm_fallback.py
council/llm/base/llm_message.py
council/llm/base/monitored_llm.py
council_ai-0.0.29.dist-info/METADATA
council_ai-0.0.29.dist-info/WHEEL
council_ai-0.0.29.dist-info/licenses/LICENSE
council_ai-0.0.29.dist-info/RECORD
