Metadata-Version: 2.4
Name: council-ai
Version: 0.0.29
Summary: Council is an open-source framework for the rapid development and robust deployment of customized generative AI applications
Project-URL: Source, https://github.com/chain-ml/council
Project-URL: Documentation, https://council.dev
License-Expression: Apache-2.0
License-File: LICENSE
Requires-Python: >=3.9
Requires-Dist: anthropic~=0.34.2
Requires-Dist: beautifulsoup4~=4.12.2
Requires-Dist: google-api-python-client>=2.106.0
Requires-Dist: google-generativeai>=0.7.0
Requires-Dist: googlenews>=1.6.10
Requires-Dist: groq~=0.12.0
Requires-Dist: httpx>=0.25.1
Requires-Dist: jinja2~=3.1.2
Requires-Dist: more-itertools~=10.0
Requires-Dist: ollama~=0.3.3
Requires-Dist: progressbar~=2.5
Requires-Dist: pydantic==2.8.*
Requires-Dist: pymediawiki~=0.7.3
Requires-Dist: python-dotenv~=1.0
Requires-Dist: pyyaml~=6.0.1
Requires-Dist: requests~=2.0
Requires-Dist: tiktoken~=0.7
Requires-Dist: toml~=0.10.2
